README.md
setup.py
sycamore/__init__.py
sycamore/core.py
sycamore.egg-info/PKG-INFO
sycamore.egg-info/SOURCES.txt
sycamore.egg-info/dependency_links.txt
sycamore.egg-info/requires.txt
sycamore.egg-info/top_level.txt