Metadata-Version: 2.1
Name: sycamore
Version: 0.0.1
Summary: 2D animation tool.
Home-page: https://github.com/brianyu28/sycamore
Author: Brian Yu
Author-email: brian@brianyu.me
License: GPL-3.0
Platform: UNKNOWN
